CHANGES.rst
MANIFEST.in
README.rst
setup.py
collective/__init__.py
collective.localstyles.egg-info/PKG-INFO
collective.localstyles.egg-info/SOURCES.txt
collective.localstyles.egg-info/dependency_links.txt
collective.localstyles.egg-info/entry_points.txt
collective.localstyles.egg-info/namespace_packages.txt
collective.localstyles.egg-info/not-zip-safe
collective.localstyles.egg-info/requires.txt
collective.localstyles.egg-info/top_level.txt
collective/localstyles/__init__.py
collective/localstyles/configure.zcml
collective/localstyles/interfaces.py
collective/localstyles/styleincluder_viewlet.pt
collective/localstyles/styleincluder_viewlet.py
collective/localstyles/profiles/default/browserlayer.xml
collective/localstyles/profiles/default/metadata.xml
collective/localstyles/profiles/uninstall/browserlayer.xml
collective/localstyles/profiles/uninstall/metadata.xml
docs/INSTALL.txt
docs/LICENSE.GPL
docs/LICENSE.txt