Metadata-Version: 1.1
Name: collective.localstyles
Version: 1.0
Summary: Add local styles to subsections in your Plone site.
Home-page: https://github.com/collective/collective.localstyles
Author: Johannes Raggam
Author-email: office@programmatic.pro
License: GPL
Keywords: plone collective theme style
Platform: UNKNOWN
Classifier: Framework :: Plone
Classifier: Programming Language :: Python
